object2urdf/__init__.py
object2urdf/object_urdf.py
object2urdf-0.12.dist-info/METADATA
object2urdf-0.12.dist-info/WHEEL
object2urdf-0.12.dist-info/top_level.txt
object2urdf-0.12.dist-info/RECORD
