Metadata-Version: 2.1
Name: object2urdf
Version: 0.12
Summary: Manage URDF files for a library of objects
Home-page: https://github.com/cbteeple/object2urdf
Author: Clark Teeple
Author-email: cbteeple@gmail.com
License: MIT
Platform: UNKNOWN
Requires-Dist: numpy
Requires-Dist: scipy
Requires-Dist: trimesh
Requires-Dist: pillow
